{
  "current_page": 1,
  "data": [
    {
      "id": 1,
      "name": "SoundFlux",
      "slug": "sound-flux",
      "brand_image_id": null,
      "brand_meta_image_id": null,
      "meta_title": "SoundFlux",
      "meta_description": "xperience cutting-edge speed and aerodynamics with Aero Edge, designed for cyclists who demand peak performance. Glide through the wind effortlessly and push your limits on every ride.",
      "brand_banner_id": null,
      "created_by_id": "1",
      "status": 1,
      "created_at": "2024-06-17T08:47:51.000000Z",
      "updated_at": "2024-06-17T08:47:51.000000Z",
      "deleted_at": null,
      "brand_image": null,
      "brand_meta_image": null,
      "brand_banner": null
    },
    {
      "id": 2,
      "name": "HearNova",
      "slug": "hear-nova",
      "brand_image_id": null,
      "brand_meta_image_id": null,
      "meta_title": "HearNova",
      "meta_description": "xperience cutting-edge speed and aerodynamics with Aero Edge, designed for cyclists who demand peak performance. Glide through the wind effortlessly and push your limits on every ride.",
      "brand_banner_id": null,
      "created_by_id": "1",
      "status": 1,
      "created_at": "2024-06-17T08:47:51.000000Z",
      "updated_at": "2024-06-17T08:47:51.000000Z",
      "deleted_at": null,
      "brand_image": null,
      "brand_meta_image": null,
      "brand_banner": null
    },
    {
      "id": 3,
      "name": "ByteCraft",
      "slug": "byte-craft",
      "brand_image_id": null,
      "brand_meta_image_id": null,
      "meta_title": "ByteCraft",
      "meta_description": "xperience cutting-edge speed and aerodynamics with Aero Edge, designed for cyclists who demand peak performance. Glide through the wind effortlessly and push your limits on every ride.",
      "brand_banner_id": null,
      "created_by_id": "1",
      "status": 1,
      "created_at": "2024-06-17T08:47:51.000000Z",
      "updated_at": "2024-06-17T08:47:51.000000Z",
      "deleted_at": null,
      "brand_image": null,
      "brand_meta_image": null,
      "brand_banner": null
    },
    {
      "id": 4,
      "name": "Compuvera",
      "slug": "compuvera",
      "brand_image_id": null,
      "brand_meta_image_id": null,
      "meta_title": "Compuvera",
      "meta_description": "xperience cutting-edge speed and aerodynamics with Aero Edge, designed for cyclists who demand peak performance. Glide through the wind effortlessly and push your limits on every ride.",
      "brand_banner_id": null,
      "created_by_id": "1",
      "status": 1,
      "created_at": "2024-06-17T08:47:51.000000Z",
      "updated_at": "2024-06-17T08:47:51.000000Z",
      "deleted_at": null,
      "brand_image": null,
      "brand_meta_image": null,
      "brand_banner": null
    },
    {
      "id": 5,
      "name": "Beautiva",
      "slug": "beautiva",
      "brand_image_id": null,
      "brand_meta_image_id": null,
      "meta_title": "Beautiva",
      "meta_description": "xperience cutting-edge speed and aerodynamics with Aero Edge, designed for cyclists who demand peak performance. Glide through the wind effortlessly and push your limits on every ride.",
      "brand_banner_id": null,
      "created_by_id": "1",
      "status": 1,
      "created_at": "2024-06-17T08:47:51.000000Z",
      "updated_at": "2024-06-17T08:47:51.000000Z",
      "deleted_at": null,
      "brand_image": null,
      "brand_meta_image": null,
      "brand_banner": null
    },
    {
      "id": 6,
      "name": "AuraGleam",
      "slug": "aura-gleam",
      "brand_image_id": null,
      "brand_meta_image_id": null,
      "meta_title": "AuraGleam",
      "meta_description": "xperience cutting-edge speed and aerodynamics with Aero Edge, designed for cyclists who demand peak performance. Glide through the wind effortlessly and push your limits on every ride.",
      "brand_banner_id": null,
      "created_by_id": "1",
      "status": 1,
      "created_at": "2024-06-17T08:47:51.000000Z",
      "updated_at": "2024-06-17T08:47:51.000000Z",
      "deleted_at": null,
      "brand_image": null,
      "brand_meta_image": null,
      "brand_banner": null
    },
    {
      "id": 7,
      "name": "StrideX",
      "slug": "stride-x",
      "brand_image_id": null,
      "brand_meta_image_id": null,
      "meta_title": "StrideX",
      "meta_description": "xperience cutting-edge speed and aerodynamics with Aero Edge, designed for cyclists who demand peak performance. Glide through the wind effortlessly and push your limits on every ride.",
      "brand_banner_id": null,
      "created_by_id": "1",
      "status": 1,
      "created_at": "2024-06-17T08:47:51.000000Z",
      "updated_at": "2024-06-17T08:47:51.000000Z",
      "deleted_at": null,
      "brand_image": null,
      "brand_meta_image": null,
      "brand_banner": null
    },
    {
      "id": 8,
      "name": "SoleVibe",
      "slug": "sole-vibe",
      "brand_image_id": null,
      "brand_meta_image_id": null,
      "meta_title": "AuraGleam",
      "meta_description": "xperience cutting-edge speed and aerodynamics with Aero Edge, designed for cyclists who demand peak performance. Glide through the wind effortlessly and push your limits on every ride.",
      "brand_banner_id": null,
      "created_by_id": "1",
      "status": 1,
      "created_at": "2024-06-17T08:47:51.000000Z",
      "updated_at": "2024-06-17T08:47:51.000000Z",
      "deleted_at": null,
      "brand_image": null,
      "brand_meta_image": null,
      "brand_banner": null
    },
    {
      "id": 9,
      "name": "PlayTribe",
      "slug": "play-tribe",
      "brand_image_id": null,
      "brand_meta_image_id": null,
      "meta_title": "PlayTribe",
      "meta_description": "xperience cutting-edge speed and aerodynamics with Aero Edge, designed for cyclists who demand peak performance. Glide through the wind effortlessly and push your limits on every ride.",
      "brand_banner_id": null,
      "created_by_id": "1",
      "status": 1,
      "created_at": "2024-06-17T08:47:51.000000Z",
      "updated_at": "2024-06-17T08:47:51.000000Z",
      "deleted_at": null,
      "brand_image": null,
      "brand_meta_image": null,
      "brand_banner": null
    },
    {
      "id": 10,
      "name": "JoyCrafter",
      "slug": "joy-crafter",
      "brand_image_id": null,
      "brand_meta_image_id": null,
      "meta_title": "JoyCrafter",
      "meta_description": "xperience cutting-edge speed and aerodynamics with Aero Edge, designed for cyclists who demand peak performance. Glide through the wind effortlessly and push your limits on every ride.",
      "brand_banner_id": null,
      "created_by_id": "1",
      "status": 1,
      "created_at": "2024-06-17T08:47:51.000000Z",
      "updated_at": "2024-06-17T08:47:51.000000Z",
      "deleted_at": null,
      "brand_image": null,
      "brand_meta_image": null,
      "brand_banner": null
    },
    {
      "id": 11,
      "name": "Trendova",
      "slug": "trendova",
      "brand_image_id": null,
      "brand_meta_image_id": null,
      "meta_title": "Trendova",
      "meta_description": "xperience cutting-edge speed and aerodynamics with Aero Edge, designed for cyclists who demand peak performance. Glide through the wind effortlessly and push your limits on every ride.",
      "brand_banner_id": null,
      "created_by_id": "1",
      "status": 1,
      "created_at": "2024-06-17T08:47:51.000000Z",
      "updated_at": "2024-06-17T08:47:51.000000Z",
      "deleted_at": null,
      "brand_image": null,
      "brand_meta_image": null,
      "brand_banner": null
    },
    {
      "id": 12,
      "name": "Fashique",
      "slug": "fashique",
      "brand_image_id": null,
      "brand_meta_image_id": null,
      "meta_title": "Fashique",
      "meta_description": "xperience cutting-edge speed and aerodynamics with Aero Edge, designed for cyclists who demand peak performance. Glide through the wind effortlessly and push your limits on every ride.",
      "brand_banner_id": null,
      "created_by_id": "1",
      "status": 1,
      "created_at": "2024-06-17T08:47:51.000000Z",
      "updated_at": "2024-06-17T08:47:51.000000Z",
      "deleted_at": null,
      "brand_image": null,
      "brand_meta_image": null,
      "brand_banner": null
    },
    {
      "id": 13,
      "name": "Callvix",
      "slug": "callvix",
      "brand_image_id": null,
      "brand_meta_image_id": null,
      "meta_title": "Callvix",
      "meta_description": "xperience cutting-edge speed and aerodynamics with Aero Edge, designed for cyclists who demand peak performance. Glide through the wind effortlessly and push your limits on every ride.",
      "brand_banner_id": null,
      "created_by_id": "1",
      "status": 1,
      "created_at": "2024-06-17T08:47:51.000000Z",
      "updated_at": "2024-06-17T08:47:51.000000Z",
      "deleted_at": null,
      "brand_image": null,
      "brand_meta_image": null,
      "brand_banner": null
    },
    {
      "id": 14,
      "name": "Mobizone",
      "slug": "mobizone",
      "brand_image_id": null,
      "brand_meta_image_id": null,
      "meta_title": "Mobizone",
      "meta_description": "xperience cutting-edge speed and aerodynamics with Aero Edge, designed for cyclists who demand peak performance. Glide through the wind effortlessly and push your limits on every ride.",
      "brand_banner_id": null,
      "created_by_id": "1",
      "status": 1,
      "created_at": "2024-06-17T08:47:51.000000Z",
      "updated_at": "2024-06-17T08:47:51.000000Z",
      "deleted_at": null,
      "brand_image": null,
      "brand_meta_image": null,
      "brand_banner": null
    },
    {
      "id": 15,
      "name": "Techora",
      "slug": "techora",
      "brand_image_id": null,
      "brand_meta_image_id": null,
      "meta_title": "Techora",
      "meta_description": "xperience cutting-edge speed and aerodynamics with Aero Edge, designed for cyclists who demand peak performance. Glide through the wind effortlessly and push your limits on every ride.",
      "brand_banner_id": null,
      "created_by_id": "1",
      "status": 1,
      "created_at": "2024-06-17T08:47:51.000000Z",
      "updated_at": "2024-06-17T08:47:51.000000Z",
      "deleted_at": null,
      "brand_image": null,
      "brand_meta_image": null,
      "brand_banner": null
    },
    {
      "id": 16,
      "name": "VoltEdge",
      "slug": "volt-edge",
      "brand_image_id": null,
      "brand_meta_image_id": null,
      "meta_title": "VoltEdge",
      "meta_description": "xperience cutting-edge speed and aerodynamics with Aero Edge, designed for cyclists who demand peak performance. Glide through the wind effortlessly and push your limits on every ride.",
      "brand_banner_id": null,
      "created_by_id": "1",
      "status": 1,
      "created_at": "2024-06-17T08:47:51.000000Z",
      "updated_at": "2024-06-17T08:47:51.000000Z",
      "deleted_at": null,
      "brand_image": null,
      "brand_meta_image": null,
      "brand_banner": null
    },
    {
      "id": 17,
      "name": "ElectraCore",
      "slug": "electra-core",
      "brand_image_id": null,
      "brand_meta_image_id": null,
      "meta_title": "ElectraCore",
      "meta_description": "xperience cutting-edge speed and aerodynamics with Aero Edge, designed for cyclists who demand peak performance. Glide through the wind effortlessly and push your limits on every ride.",
      "brand_banner_id": null,
      "created_by_id": "1",
      "status": 1,
      "created_at": "2024-06-17T08:47:51.000000Z",
      "updated_at": "2024-06-17T08:47:51.000000Z",
      "deleted_at": null,
      "brand_image": null,
      "brand_meta_image": null,
      "brand_banner": null
    },
    {
      "id": 18,
      "name": "Luxora",
      "slug": "luxora",
      "brand_image_id": null,
      "brand_meta_image_id": null,
      "meta_title": "Luxora",
      "meta_description": "xperience cutting-edge speed and aerodynamics with Aero Edge, designed for cyclists who demand peak performance. Glide through the wind effortlessly and push your limits on every ride.",
      "brand_banner_id": null,
      "created_by_id": "1",
      "status": 1,
      "created_at": "2024-06-17T08:47:51.000000Z",
      "updated_at": "2024-06-17T08:47:51.000000Z",
      "deleted_at": null,
      "brand_image": null,
      "brand_meta_image": null,
      "brand_banner": null
    }
  ],
  "from": 1,
  "last_page": 1,
  "links": [
    {
      "url": null,
      "label": "&laquo; Previous",
      "active": false
    },
    {
      "label": "1",
      "active": true
    },
    {
      "url": null,
      "label": "Next &raquo;",
      "active": false
    }
  ],
  "next_page_url": null,
  "per_page": 80,
  "prev_page_url": null,
  "to": 80,
  "total": 80
}
